.coveragerc
.pylintrc
MANIFEST.in
README.rst
devutils_requirements.txt
setup.cfg
setup.py
tox.ini
sphinxdocs/CHANGES.rst
sphinxdocs/README.rst
sphinxdocs/cli.rst
sphinxdocs/conf.py
sphinxdocs/index.rst
sphinxdocs/programmatic.rst
sphinxdocs/requirements.txt
src/virtualenvrunner/__init__.py
src/virtualenvrunner/_version.py
src/virtualenvrunner/activateenv.py
src/virtualenvrunner/cli.py
src/virtualenvrunner/python_versions.py
src/virtualenvrunner/pythonversionrun.py
src/virtualenvrunner/runner.py
src/virtualenvrunner/runnerargparser.py
src/virtualenvrunner/utils.py
src/virtualenvrunner.egg-info/PKG-INFO
src/virtualenvrunner.egg-info/SOURCES.txt
src/virtualenvrunner.egg-info/dependency_links.txt
src/virtualenvrunner.egg-info/entry_points.txt
src/virtualenvrunner.egg-info/requires.txt
src/virtualenvrunner.egg-info/top_level.txt
tests/__init__.py
tests/conftest.py
tests/test_activateenv.py
tests/test_cli.py
tests/test_runner.py
tests/mockvenv/bin/activate_this.py
tests/mockwinvenv/Scripts/activate_this.py