Metadata-Version: 1.1
Name: virtualenvrunner
Version: 1.1.1
Summary: Runner for shell commands in virtualenv
Home-page: https://github.com/nokia/virtualenvrunner
Author: Petri Huovinen
Author-email: petri.huovinen@nokia.com
License: BSD 3-Clause
Keywords: virtualenv
Platform: UNKNOWN
Classifier: Intended Audience :: Developers
Classifier: License :: OSI Approved :: BSD License
Classifier: Programming Language :: Python :: 2
Classifier: Programming Language :: Python :: 2.7
Classifier: Programming Language :: Python :: 3
Classifier: Programming Language :: Python :: 3.6
Classifier: Topic :: Software Development
